genbooster-0.6.8.dist-info/METADATA
genbooster-0.6.8.dist-info/WHEEL
genbooster-0.6.8.dist-info/licenses/LICENSE
genbooster/__init__.py
genbooster/adaboostclassifier.py
genbooster/adaboostregressor.py
genbooster/genboosterclassifier.py
genbooster/genboosterregressor.py
genbooster/randombagclassifier.py
genbooster/randombagregressor.py
genbooster/regressionmodels.py
genbooster/rust_core.cpython-38-x86_64-linux-gnu.so
genbooster-0.6.8.dist-info/RECORD
