Metadata-Version: 2.4
Name: genbooster
Version: 0.6.8
Classifier: Programming Language :: Python :: 3
Classifier: Programming Language :: Rust
Classifier: License :: OSI Approved :: BSD License
Classifier: Operating System :: OS Independent
Requires-Dist: nnetsauce
Requires-Dist: numpy>=1.20.0
Requires-Dist: pandas
Requires-Dist: scikit-learn>=1.0.0
License-File: LICENSE
Summary: A fast boosting implementation using Rust and Python
Author-email: "T. Moudiki" <thierry.moudiki@gmail.com>
Requires-Python: >=3.7
Project-URL: Repository, https://github.com/yourusername/genbooster
